folium_vectorgrid/__init__.py
folium_vectorgrid/vectorgrid.py
folium_vectorgrid-1.0.0.dist-info/METADATA
folium_vectorgrid-1.0.0.dist-info/WHEEL
folium_vectorgrid-1.0.0.dist-info/licenses/LICENSE
folium_vectorgrid-1.0.0.dist-info/RECORD
