Metadata-Version: 2.4
Name: folium-vectorgrid
Version: 1.0.0
Summary: vectorgrid plugin for folium
Project-URL: Homepage, https://iwpnd.github.io/folium-vectorgrid/
Project-URL: Repository, https://github.com/iwpnd/folium-vectorgrid
Project-URL: Documentation, https://iwpnd.github.io/folium-vectorgrid/
Author-email: Benjamin Ramser <iwpnd@posteo.de>
License-File: LICENSE
Keywords: python
Classifier: Intended Audience :: Developers
Classifier: Programming Language :: Python
Classifier: Programming Language :: Python :: 3
Classifier: Programming Language :: Python :: 3.10
Classifier: Programming Language :: Python :: 3.11
Classifier: Programming Language :: Python :: 3.12
Classifier: Programming Language :: Python :: 3.13
Classifier: Topic :: Software Development :: Libraries :: Python Modules
Requires-Python: <4.0,>=3.10
Requires-Dist: folium>=0.19.5
